approval_utilities/__init__.py
approval_utilities/list_utils.py
approval_utilities/py.typed
approval_utilities/utils.py
approval_utilities/approvaltests/__init__.py
approval_utilities/approvaltests/core/__init__.py
approval_utilities/approvaltests/core/executable_command.py
approval_utilities/approvaltests/core/verifiable.py
approval_utilities/approvaltests/core/verify_parameters.py
approval_utilities/utilities/__init__.py
approval_utilities/utilities/clipboard_utilities.py
approval_utilities/utilities/deprecated.py
approval_utilities/utilities/map_reduce.py
approval_utilities/utilities/markdown_table.py
approval_utilities/utilities/multiline_string_utils.py
approval_utilities/utilities/os_utilities.py
approval_utilities/utilities/stack_frame_utilities.py
approval_utilities/utilities/string_wrapper.py
approval_utilities/utilities/time_utilities.py
approval_utilities/utilities/wrapper.py
approval_utilities/utilities/exceptions/__init__.py
approval_utilities/utilities/exceptions/exception_collector.py
approval_utilities/utilities/exceptions/exception_utils.py
approval_utilities/utilities/exceptions/multiple_exceptions.py
approval_utilities/utilities/logger/__init__.py
approval_utilities/utilities/logger/logging_instance.py
approval_utilities/utilities/logger/simple_logger.py
approval_utilities/utilities/persistence/__init__.py
approval_utilities/utilities/persistence/loader.py
approval_utilities/utilities/persistence/saver.py
approvaltests/__init__.py
approvaltests/__main__.py
approvaltests/approval_exception.py
approvaltests/approvals.py
approvaltests/asserts.py
approvaltests/binary_writer.py
approvaltests/combination_approvals.py
approvaltests/command.py
approvaltests/commandline_interface.py
approvaltests/existing_file_writer.py
approvaltests/file_approver.py
approvaltests/pairwise_combinations.py
approvaltests/py.typed
approvaltests/reporter_missing_exception.py
approvaltests/storyboard.py
approvaltests/string_writer.py
approvaltests/version.py
approvaltests_minimal-16.3.0.dist-info/licenses/LICENSE
approvaltests_minimal-16.3.0.dist-info/METADATA
approvaltests_minimal-16.3.0.dist-info/WHEEL
approvaltests_minimal-16.3.0.dist-info/entry_points.txt
approvaltests_minimal-16.3.0.dist-info/top_level.txt
approvaltests_minimal-16.3.0.dist-info/RECORD
