Metadata-Version: 2.4
Name: approvaltests-minimal
Version: 16.3.0
Summary: Assertion/verification library to aid testing with the minimal required dependencies + the ability to opt in for the others 
Home-page: https://github.com/approvals/ApprovalTests.Python
Author: ApprovalTests Contributors
Author-email: llewellyn.falco@gmail.com
Classifier: Development Status :: 4 - Beta
Classifier: Intended Audience :: Developers
Classifier: License :: OSI Approved :: Apache Software License
Classifier: Operating System :: POSIX
Classifier: Operating System :: Microsoft :: Windows
Classifier: Operating System :: MacOS :: MacOS X
Classifier: Programming Language :: Python :: 3
Classifier: Programming Language :: Python :: 3 :: Only
Classifier: Programming Language :: Python :: 3.8
Classifier: Programming Language :: Python :: 3.9
Classifier: Programming Language :: Python :: 3.10
Classifier: Programming Language :: Python :: 3.11
Classifier: Topic :: Software Development :: Libraries
Classifier: Topic :: Software Development :: Testing
Classifier: Topic :: Utilities
Requires-Python: >=3.8
License-File: LICENSE
Requires-Dist: pytest>=4.0.0
Requires-Dist: empty-files>=0.0.3
Requires-Dist: typing_extensions>=3.6.2
Provides-Extra: clipboardreporter
Requires-Dist: pyperclip; extra == "clipboardreporter"
Provides-Extra: verify-html
Requires-Dist: beautifulsoup4; extra == "verify-html"
Provides-Extra: pairwisecombinations
Requires-Dist: allpairspy; extra == "pairwisecombinations"
Dynamic: author
Dynamic: author-email
Dynamic: classifier
Dynamic: description
Dynamic: description-content-type
Dynamic: home-page
Dynamic: license-file
Dynamic: provides-extra
Dynamic: requires-dist
Dynamic: requires-python
Dynamic: summary
